{
  "views": [
    {
      "timestamp": "2025-07-24T15:06:35.335972",
      "count": 101,
      "uniques": 2,
      "views": [
        {
          "timestamp": "2025-07-23T00:00:00Z",
          "count": 72,
          "uniques": 2
        },
        {
          "timestamp": "2025-07-24T00:00:00Z",
          "count": 29,
          "uniques": 1
        }
      ]
    },
    {
      "timestamp": "2025-07-25T01:37:23.370809",
      "count": 171,
      "uniques": 3,
      "views": [
        {
          "timestamp": "2025-07-23T00:00:00Z",
          "count": 72,
          "uniques": 2
        },
        {
          "timestamp": "2025-07-24T00:00:00Z",
          "count": 99,
          "uniques": 2
        }
      ]
    },
    {
      "timestamp": "2025-07-26T01:36:45.715031",
      "count": 184,
      "uniques": 3,
      "views": [
        {
          "timestamp": "2025-07-23T00:00:00Z",
          "count": 72,
          "uniques": 2
        },
        {
          "timestamp": "2025-07-24T00:00:00Z",
          "count": 99,
          "uniques": 2
        },
        {
          "timestamp": "2025-07-25T00:00:00Z",
          "count": 13,
          "uniques": 1
        }
      ]
    },
    {
      "timestamp": "2025-07-27T01:37:38.327855",
      "count": 184,
      "uniques": 3,
      "views": [
        {
          "timestamp": "2025-07-23T00:00:00Z",
          "count": 72,
          "uniques": 2
        },
        {
          "timestamp": "2025-07-24T00:00:00Z",
          "count": 99,
          "uniques": 2
        },
        {
          "timestamp": "2025-07-25T00:00:00Z",
          "count": 13,
          "uniques": 1
        }
      ]
    },
    {
      "timestamp": "2025-07-28T01:38:16.293618",
      "count": 200,
      "uniques": 3,
      "views": [
        {
          "timestamp": "2025-07-23T00:00:00Z",
          "count": 72,
          "uniques": 2
        },
        {
          "timestamp": "2025-07-24T00:00:00Z",
          "count": 99,
          "uniques": 2
        },
        {
          "timestamp": "2025-07-25T00:00:00Z",
          "count": 13,
          "uniques": 1
        },
        {
          "timestamp": "2025-07-27T00:00:00Z",
          "count": 16,
          "uniques": 1
        }
      ]
    }
  ],
  "clones": [
    {
      "timestamp": "2025-07-24T15:06:35.335972",
      "count": 93,
      "uniques": 42,
      "clones": [
        {
          "timestamp": "2025-07-23T00:00:00Z",
          "count": 80,
          "uniques": 39
        },
        {
          "timestamp": "2025-07-24T00:00:00Z",
          "count": 13,
          "uniques": 7
        }
      ]
    },
    {
      "timestamp": "2025-07-25T01:37:23.370809",
      "count": 125,
      "uniques": 54,
      "clones": [
        {
          "timestamp": "2025-07-23T00:00:00Z",
          "count": 80,
          "uniques": 39
        },
        {
          "timestamp": "2025-07-24T00:00:00Z",
          "count": 39,
          "uniques": 17
        },
        {
          "timestamp": "2025-07-25T00:00:00Z",
          "count": 6,
          "uniques": 5
        }
      ]
    },
    {
      "timestamp": "2025-07-26T01:36:45.715031",
      "count": 140,
      "uniques": 58,
      "clones": [
        {
          "timestamp": "2025-07-23T00:00:00Z",
          "count": 80,
          "uniques": 39
        },
        {
          "timestamp": "2025-07-24T00:00:00Z",
          "count": 39,
          "uniques": 17
        },
        {
          "timestamp": "2025-07-25T00:00:00Z",
          "count": 14,
          "uniques": 9
        },
        {
          "timestamp": "2025-07-26T00:00:00Z",
          "count": 7,
          "uniques": 6
        }
      ]
    },
    {
      "timestamp": "2025-07-27T01:37:38.327855",
      "count": 161,
      "uniques": 65,
      "clones": [
        {
          "timestamp": "2025-07-23T00:00:00Z",
          "count": 80,
          "uniques": 39
        },
        {
          "timestamp": "2025-07-24T00:00:00Z",
          "count": 39,
          "uniques": 17
        },
        {
          "timestamp": "2025-07-25T00:00:00Z",
          "count": 14,
          "uniques": 9
        },
        {
          "timestamp": "2025-07-26T00:00:00Z",
          "count": 21,
          "uniques": 12
        },
        {
          "timestamp": "2025-07-27T00:00:00Z",
          "count": 7,
          "uniques": 6
        }
      ]
    },
    {
      "timestamp": "2025-07-28T01:38:16.293618",
      "count": 179,
      "uniques": 70,
      "clones": [
        {
          "timestamp": "2025-07-23T00:00:00Z",
          "count": 80,
          "uniques": 39
        },
        {
          "timestamp": "2025-07-24T00:00:00Z",
          "count": 39,
          "uniques": 17
        },
        {
          "timestamp": "2025-07-25T00:00:00Z",
          "count": 14,
          "uniques": 9
        },
        {
          "timestamp": "2025-07-26T00:00:00Z",
          "count": 21,
          "uniques": 12
        },
        {
          "timestamp": "2025-07-27T00:00:00Z",
          "count": 19,
          "uniques": 11
        },
        {
          "timestamp": "2025-07-28T00:00:00Z",
          "count": 6,
          "uniques": 5
        }
      ]
    }
  ],
  "referrers": [
    {
      "timestamp": "2025-07-24T15:06:35.335972",
      "data": [
        {
          "referrer": "github.com",
          "count": 39,
          "uniques": 1
        },
        {
          "referrer": "th3nolo.github.io",
          "count": 17,
          "uniques": 1
        },
        {
          "referrer": "gemini.google.com",
          "count": 2,
          "uniques": 1
        }
      ]
    },
    {
      "timestamp": "2025-07-25T01:37:23.370809",
      "data": [
        {
          "referrer": "github.com",
          "count": 39,
          "uniques": 1
        },
        {
          "referrer": "th3nolo.github.io",
          "count": 17,
          "uniques": 1
        },
        {
          "referrer": "gemini.google.com",
          "count": 2,
          "uniques": 1
        }
      ]
    },
    {
      "timestamp": "2025-07-26T01:36:45.715031",
      "data": [
        {
          "referrer": "github.com",
          "count": 80,
          "uniques": 1
        },
        {
          "referrer": "th3nolo.github.io",
          "count": 17,
          "uniques": 1
        },
        {
          "referrer": "gemini.google.com",
          "count": 2,
          "uniques": 1
        }
      ]
    },
    {
      "timestamp": "2025-07-27T01:37:38.327855",
      "data": [
        {
          "referrer": "github.com",
          "count": 93,
          "uniques": 1
        },
        {
          "referrer": "th3nolo.github.io",
          "count": 17,
          "uniques": 1
        },
        {
          "referrer": "gemini.google.com",
          "count": 2,
          "uniques": 1
        }
      ]
    },
    {
      "timestamp": "2025-07-28T01:38:16.293618",
      "data": [
        {
          "referrer": "github.com",
          "count": 93,
          "uniques": 1
        },
        {
          "referrer": "th3nolo.github.io",
          "count": 17,
          "uniques": 1
        },
        {
          "referrer": "gemini.google.com",
          "count": 2,
          "uniques": 1
        }
      ]
    }
  ],
  "paths": [
    {
      "timestamp": "2025-07-24T15:06:35.335972",
      "data": [
        {
          "path": "/th3nolo/aave-v3-data",
          "title": "th3nolo/aave-v3-data: Aave V3 Protocol Data API - Real-time DeFi reserves, le...",
          "count": 32,
          "uniques": 2
        },
        {
          "path": "/th3nolo/aave-v3-data/commits/main",
          "title": "Commits \u00b7 th3nolo/aave-v3-data",
          "count": 8,
          "uniques": 1
        },
        {
          "path": "/th3nolo/aave-v3-data/blob/main/traffic_data/TRAFFIC_REPORT.md",
          "title": "aave-v3-data/traffic_data/TRAFFIC_REPORT.md at main \u00b7 th3nolo/aave-v3-data",
          "count": 4,
          "uniques": 1
        },
        {
          "path": "/th3nolo/aave-v3-data/actions/metrics/performance",
          "title": "Actions Performance Metrics",
          "count": 2,
          "uniques": 1
        },
        {
          "path": "/th3nolo/aave-v3-data/graphs/traffic",
          "title": "Traffic \u00b7 th3nolo/aave-v3-data",
          "count": 2,
          "uniques": 1
        },
        {
          "path": "/th3nolo/aave-v3-data/pulse",
          "title": "Pulse \u00b7 th3nolo/aave-v3-data",
          "count": 2,
          "uniques": 1
        },
        {
          "path": "/th3nolo/aave-v3-data/releases",
          "title": "Releases \u00b7 th3nolo/aave-v3-data",
          "count": 2,
          "uniques": 1
        },
        {
          "path": "/th3nolo/aave-v3-data/tags",
          "title": "Tags \u00b7 th3nolo/aave-v3-data",
          "count": 2,
          "uniques": 1
        },
        {
          "path": "/th3nolo/aave-v3-data/actions",
          "title": "Workflow runs \u00b7 th3nolo/aave-v3-data",
          "count": 1,
          "uniques": 1
        },
        {
          "path": "/th3nolo/aave-v3-data/actions/metrics/usage",
          "title": "Actions Usage Metrics",
          "count": 1,
          "uniques": 1
        }
      ]
    },
    {
      "timestamp": "2025-07-25T01:37:23.370809",
      "data": [
        {
          "path": "/th3nolo/aave-v3-data",
          "title": "th3nolo/aave-v3-data: Aave V3 Protocol Data API - Real-time DeFi reserves, le...",
          "count": 32,
          "uniques": 2
        },
        {
          "path": "/th3nolo/aave-v3-data/commits/main",
          "title": "Commits \u00b7 th3nolo/aave-v3-data",
          "count": 8,
          "uniques": 1
        },
        {
          "path": "/th3nolo/aave-v3-data/blob/main/traffic_data/TRAFFIC_REPORT.md",
          "title": "aave-v3-data/traffic_data/TRAFFIC_REPORT.md at main \u00b7 th3nolo/aave-v3-data",
          "count": 4,
          "uniques": 1
        },
        {
          "path": "/th3nolo/aave-v3-data/actions/metrics/performance",
          "title": "Actions Performance Metrics",
          "count": 2,
          "uniques": 1
        },
        {
          "path": "/th3nolo/aave-v3-data/graphs/traffic",
          "title": "Traffic \u00b7 th3nolo/aave-v3-data",
          "count": 2,
          "uniques": 1
        },
        {
          "path": "/th3nolo/aave-v3-data/pulse",
          "title": "Pulse \u00b7 th3nolo/aave-v3-data",
          "count": 2,
          "uniques": 1
        },
        {
          "path": "/th3nolo/aave-v3-data/releases",
          "title": "Releases \u00b7 th3nolo/aave-v3-data",
          "count": 2,
          "uniques": 1
        },
        {
          "path": "/th3nolo/aave-v3-data/tags",
          "title": "Tags \u00b7 th3nolo/aave-v3-data",
          "count": 2,
          "uniques": 1
        },
        {
          "path": "/th3nolo/aave-v3-data/actions",
          "title": "Workflow runs \u00b7 th3nolo/aave-v3-data",
          "count": 1,
          "uniques": 1
        },
        {
          "path": "/th3nolo/aave-v3-data/actions/metrics/usage",
          "title": "Actions Usage Metrics",
          "count": 1,
          "uniques": 1
        }
      ]
    },
    {
      "timestamp": "2025-07-26T01:36:45.715031",
      "data": [
        {
          "path": "/th3nolo/aave-v3-data",
          "title": "th3nolo/aave-v3-data: Aave V3 Protocol Data API - Real-time DeFi reserves, le...",
          "count": 50,
          "uniques": 3
        },
        {
          "path": "/th3nolo/aave-v3-data/commits/main",
          "title": "Commits \u00b7 th3nolo/aave-v3-data",
          "count": 17,
          "uniques": 2
        },
        {
          "path": "/th3nolo/aave-v3-data/actions/metrics/usage",
          "title": "Actions Usage Metrics",
          "count": 8,
          "uniques": 1
        },
        {
          "path": "/th3nolo/aave-v3-data/actions/workflows/traffic-analytics.yml",
          "title": ".github/workflows/traffic-analytics.yml \u00b7 Workflow runs \u00b7 th3nolo/aave-v3-data",
          "count": 8,
          "uniques": 1
        },
        {
          "path": "/th3nolo/aave-v3-data/actions",
          "title": "Workflow runs \u00b7 th3nolo/aave-v3-data",
          "count": 6,
          "uniques": 1
        },
        {
          "path": "/th3nolo/aave-v3-data/blob/main/traffic_data/TRAFFIC_REPORT.md",
          "title": "aave-v3-data/traffic_data/TRAFFIC_REPORT.md at main \u00b7 th3nolo/aave-v3-data",
          "count": 6,
          "uniques": 1
        },
        {
          "path": "/th3nolo/aave-v3-data/actions/runs/16484624965",
          "title": "Update Aave V3 Data \u00b7 th3nolo/aave-v3-data@7c3c5ec",
          "count": 4,
          "uniques": 1
        },
        {
          "path": "/th3nolo/aave-v3-data/deployments",
          "title": "Deployments \u00b7 th3nolo/aave-v3-data",
          "count": 3,
          "uniques": 1
        },
        {
          "path": "/th3nolo/aave-v3-data/deployments/github-pages",
          "title": "Deployments \u00b7 th3nolo/aave-v3-data",
          "count": 3,
          "uniques": 1
        },
        {
          "path": "/th3nolo/aave-v3-data/graphs/traffic",
          "title": "Traffic \u00b7 th3nolo/aave-v3-data",
          "count": 3,
          "uniques": 1
        }
      ]
    },
    {
      "timestamp": "2025-07-27T01:37:38.327855",
      "data": [
        {
          "path": "/th3nolo/aave-v3-data",
          "title": "th3nolo/aave-v3-data: Aave V3 Protocol Data API - Real-time DeFi reserves, le...",
          "count": 55,
          "uniques": 3
        },
        {
          "path": "/th3nolo/aave-v3-data/commits/main",
          "title": "Commits \u00b7 th3nolo/aave-v3-data",
          "count": 19,
          "uniques": 2
        },
        {
          "path": "/th3nolo/aave-v3-data/actions/metrics/usage",
          "title": "Actions Usage Metrics",
          "count": 8,
          "uniques": 1
        },
        {
          "path": "/th3nolo/aave-v3-data/actions/workflows/traffic-analytics.yml",
          "title": ".github/workflows/traffic-analytics.yml \u00b7 Workflow runs \u00b7 th3nolo/aave-v3-data",
          "count": 8,
          "uniques": 1
        },
        {
          "path": "/th3nolo/aave-v3-data/blob/main/traffic_data/TRAFFIC_REPORT.md",
          "title": "aave-v3-data/traffic_data/TRAFFIC_REPORT.md at main \u00b7 th3nolo/aave-v3-data",
          "count": 7,
          "uniques": 1
        },
        {
          "path": "/th3nolo/aave-v3-data/actions",
          "title": "Workflow runs \u00b7 th3nolo/aave-v3-data",
          "count": 6,
          "uniques": 1
        },
        {
          "path": "/th3nolo/aave-v3-data/actions/runs/16484624965",
          "title": "Update Aave V3 Data \u00b7 th3nolo/aave-v3-data@7c3c5ec",
          "count": 4,
          "uniques": 1
        },
        {
          "path": "/th3nolo/aave-v3-data/pulse",
          "title": "Pulse \u00b7 th3nolo/aave-v3-data",
          "count": 4,
          "uniques": 1
        },
        {
          "path": "/th3nolo/aave-v3-data/commit/ff463d053f8231306cec2ace2f553ddd5773f03c",
          "title": "Update traffic analytics - 2025-07-24 \u00b7 th3nolo/aave-v3-data@ff463d0",
          "count": 3,
          "uniques": 1
        },
        {
          "path": "/th3nolo/aave-v3-data/deployments",
          "title": "Deployments \u00b7 th3nolo/aave-v3-data",
          "count": 3,
          "uniques": 1
        }
      ]
    },
    {
      "timestamp": "2025-07-28T01:38:16.293618",
      "data": [
        {
          "path": "/th3nolo/aave-v3-data",
          "title": "th3nolo/aave-v3-data: Aave V3 Protocol Data API - Real-time DeFi reserves, le...",
          "count": 55,
          "uniques": 3
        },
        {
          "path": "/th3nolo/aave-v3-data/commits/main",
          "title": "Commits \u00b7 th3nolo/aave-v3-data",
          "count": 19,
          "uniques": 2
        },
        {
          "path": "/th3nolo/aave-v3-data/actions/metrics/usage",
          "title": "Actions Usage Metrics",
          "count": 8,
          "uniques": 1
        },
        {
          "path": "/th3nolo/aave-v3-data/actions/workflows/traffic-analytics.yml",
          "title": ".github/workflows/traffic-analytics.yml \u00b7 Workflow runs \u00b7 th3nolo/aave-v3-data",
          "count": 8,
          "uniques": 1
        },
        {
          "path": "/th3nolo/aave-v3-data/blob/main/traffic_data/TRAFFIC_REPORT.md",
          "title": "aave-v3-data/traffic_data/TRAFFIC_REPORT.md at main \u00b7 th3nolo/aave-v3-data",
          "count": 7,
          "uniques": 1
        },
        {
          "path": "/th3nolo/aave-v3-data/actions",
          "title": "Workflow runs \u00b7 th3nolo/aave-v3-data",
          "count": 6,
          "uniques": 1
        },
        {
          "path": "/th3nolo/aave-v3-data/actions/runs/16484624965",
          "title": "Update Aave V3 Data \u00b7 th3nolo/aave-v3-data@7c3c5ec",
          "count": 4,
          "uniques": 1
        },
        {
          "path": "/th3nolo/aave-v3-data/pulse",
          "title": "Pulse \u00b7 th3nolo/aave-v3-data",
          "count": 4,
          "uniques": 1
        },
        {
          "path": "/th3nolo/aave-v3-data/commit/ff463d053f8231306cec2ace2f553ddd5773f03c",
          "title": "Update traffic analytics - 2025-07-24 \u00b7 th3nolo/aave-v3-data@ff463d0",
          "count": 3,
          "uniques": 1
        },
        {
          "path": "/th3nolo/aave-v3-data/deployments",
          "title": "Deployments \u00b7 th3nolo/aave-v3-data",
          "count": 3,
          "uniques": 1
        }
      ]
    }
  ]
}